<?xml version="1.0" encoding="utf-8"?>
<search>
  
  
  
  <entry>
    <title>About-C++</title>
    <link href="/2022/08/01/About-C/"/>
    <url>/2022/08/01/About-C/</url>
    
    <content type="html"><![CDATA[<h1 id="1-指针"><a href="#1-指针" class="headerlink" title="1.指针"></a>1.指针</h1><p>指针本身是一个对象，但是它又指向另一个对象，这是指针的两种属性</p><ul><li><p>指针本身是一个常量，指针的指向也是一个常量，也就是说不能改变指针的指向，称其为顶层const(top-level const )</p></li><li><p>顶层const 表示指针本身就是一个常量</p><figure class="highlight c++"><table><tr><td class="gutter"><pre><span class="line">1</span><br></pre></td><td class="code"><pre><code class="hljs C++"><span class="hljs-type">int</span>* cosnt p1 = &amp;a;<span class="hljs-comment">//p1是顶层const</span><br></code></pre></td></tr></table></figure><p>​</p></li><li><p>指针指向的对象是一个常量，即指针指向的地址的值是一个常量，不能改变指针指向内存的值，称为底层const(low-level const）</p></li><li><p>底层const表示指针指向的对象是一个常量</p><figure class="highlight c++"><table><tr><td class="gutter"><pre><span class="line">1</span><br></pre></td><td class="code"><pre><code class="hljs c++">cosnt <span class="hljs-type">int</span>* p2 = &amp;a;<span class="hljs-comment">//p2是底层const</span><br></code></pre></td></tr></table></figure><p>​</p></li></ul><figure class="highlight c++"><table><tr><td class="gutter"><pre><span class="line">1</span><br><span class="line">2</span><br><span class="line">3</span><br><span class="line">4</span><br><span class="line">5</span><br><span class="line">6</span><br></pre></td><td class="code"><pre><code class="hljs c++"><span class="hljs-type">int</span> i = <span class="hljs-number">0</span>;<br><span class="hljs-type">int</span> *<span class="hljs-type">const</span> p1 = &amp;i;       <span class="hljs-comment">// 不能改变p1的值，这是一个顶层const</span><br><span class="hljs-type">const</span> <span class="hljs-type">int</span> ci = <span class="hljs-number">42</span>;        <span class="hljs-comment">// 不能改变ci的值，这是一个顶层const</span><br><span class="hljs-type">const</span> <span class="hljs-type">int</span> *p2 = &amp;ci;      <span class="hljs-comment">// 允许改变p2的值，这是一个底层const</span><br><span class="hljs-type">const</span> <span class="hljs-type">int</span> *<span class="hljs-type">const</span> p3 = p2; <span class="hljs-comment">// 靠右的const是顶层const，靠左的const是底层const</span><br><span class="hljs-type">const</span> <span class="hljs-type">int</span> &amp;r = ci;        <span class="hljs-comment">// 用于声明引用的const都是底层const</span><br></code></pre></td></tr></table></figure><h2 id="指向常量的引用"><a href="#指向常量的引用" class="headerlink" title="指向常量的引用"></a>指向常量的引用</h2><p>程序里有一个<strong>对象r</strong>（C++里对象即变量，可以理解为同义词），现在我想设置一个<strong>【引用】</strong>来<strong>【绑定】</strong>它，但有一个要求：不能<strong>【通过这个引用】</strong>来<strong>【修改】</strong>这个对象的值，但允许通过这个引用来<strong>【读取】</strong>这个对象。</p><figure class="highlight c++"><table><tr><td class="gutter"><pre><span class="line">1</span><br><span class="line">2</span><br><span class="line">3</span><br><span class="line">4</span><br></pre></td><td class="code"><pre><code class="hljs c++"><span class="hljs-type">int</span> r = <span class="hljs-number">1</span>;<br><span class="hljs-type">const</span> <span class="hljs-type">int</span> &amp;R = r;  <span class="hljs-comment">//引用R绑定了r</span><br>cout &lt;&lt; R;  <span class="hljs-comment">//正确：允许通过引用R读取r的值</span><br>R = <span class="hljs-number">2</span>;      <span class="hljs-comment">//错误：终端提示“ assignment of read-only reference &#x27;R&#x27; ”</span><br></code></pre></td></tr></table></figure><h2 id="指向常量的指针"><a href="#指向常量的指针" class="headerlink" title="指向常量的指针"></a>指向常量的指针</h2><p>程序里有一个<strong>对象r</strong>，现在我想设置一个<strong>【指针】</strong>来<strong>【指向】</strong>它，但有一个要求：不能<strong>【通过这个指针】</strong>来<strong>【修改】</strong>这个对象的值，但允许通过这个指针来<strong>【读取】</strong>这个对象。</p><figure class="highlight c++"><table><tr><td class="gutter"><pre><span class="line">1</span><br><span class="line">2</span><br><span class="line">3</span><br><span class="line">4</span><br></pre></td><td class="code"><pre><code class="hljs c++"><span class="hljs-type">int</span> r = <span class="hljs-number">1</span>;<br><span class="hljs-type">const</span> <span class="hljs-type">int</span> *p = &amp;r;  <span class="hljs-comment">//指针p指向了r</span><br>cout &lt;&lt; *p;  <span class="hljs-comment">//正确：允许通过指针p读取r的值</span><br>*p = <span class="hljs-number">2</span>;      <span class="hljs-comment">//错误：终端提示“ assignment of read-only location &#x27;* p&#x27; ”</span><br></code></pre></td></tr></table></figure><h2 id="常量指针"><a href="#常量指针" class="headerlink" title="常量指针"></a>常量指针</h2><p>房子里面的东西可以变，房子的地址不能变</p><p>指向不能变</p><figure class="highlight c++"><table><tr><td class="gutter"><pre><span class="line">1</span><br><span class="line">2</span><br><span class="line">3</span><br><span class="line">4</span><br><span class="line">5</span><br></pre></td><td class="code"><pre><code class="hljs c++"><span class="hljs-type">int</span> x = <span class="hljs-number">1</span>, y = <span class="hljs-number">10</span>;<br><span class="hljs-type">int</span> *<span class="hljs-type">const</span> p = &amp;x;  <span class="hljs-comment">//指针p指向了x</span><br>*p = <span class="hljs-number">2</span>;     <span class="hljs-comment">//正确：允许通过指针p读取和修改x的值</span><br>p = &amp;y;     <span class="hljs-comment">//错误：终端提示“ assignment of read-only variable &#x27;p&#x27; ”</span><br><br></code></pre></td></tr></table></figure><h2 id="指针和引用的区别"><a href="#指针和引用的区别" class="headerlink" title="指针和引用的区别"></a>指针和引用的区别</h2><ol><li><p>引用不是对象，不分配内存。 指针是对象，分配内存</p><p>引用定义时必须初始化，且只与初始时的对象所绑定，作为该对象的<strong>别名</strong>【而指针本身就是一个<strong>对象</strong>，使用<code>size(引用)</code>得到的是所绑定的对象的类型大小，而<code>sizeof(指针)</code>得到的是这个指针对象本身的类型大小】。</p></li><li><p>引用是类型安全的，而指针不是</p><p>由于必须初始化且与一个对象一直绑定，因此不存在空引用，但指针指向可以随意更改（指针其实也可以理解为一个普通变量，只不过它的变量值是一个地址值，较特别），且允许存在空指针和野指针（野指针可以在多种场景下产生，其中一种情况是当多个指针指向一块内存，free掉一个指针之后，那么别的指针就成为了野指针）。因此引用是类型安全的，而指针不是。类型安全即内存安全。</p></li></ol><h1 id="2-关于const"><a href="#2-关于const" class="headerlink" title="2.关于const"></a>2.关于const</h1><ul><li><p><strong>底层const</strong>:若【通过】<strong>某</strong>【指针&#x2F;引用】<strong>无法对所</strong>【指向&#x2F;绑定】<strong>的对象进行</strong>【值修改】，我们就称该【指针&#x2F;引用】为一个<code>底层const</code></p><figure class="highlight c++"><table><tr><td class="gutter"><pre><span class="line">1</span><br><span class="line">2</span><br><span class="line">3</span><br><span class="line">4</span><br><span class="line">5</span><br><span class="line">6</span><br></pre></td><td class="code"><pre><code class="hljs c++"><span class="hljs-type">const</span> <span class="hljs-type">int</span> m = <span class="hljs-number">1</span>;<br><span class="hljs-type">int</span> &amp;M = m;         <span class="hljs-comment">//错误：普通的int&amp;不能绑定到int整型常量上（反证法：如果可以，那通过M就能修改m的值，这样就和m是常量的规定发生冲突）</span><br><span class="hljs-type">int</span> r = <span class="hljs-number">2</span>;<br><span class="hljs-type">const</span> <span class="hljs-type">int</span> &amp;R = r;   <span class="hljs-comment">//这就是上面的例子。等号右侧的表达式`r`其类型是`int整型`，可以转换成int整型常量`，因此不会报错</span><br><span class="hljs-type">const</span> <span class="hljs-type">int</span> &amp;x = <span class="hljs-number">10</span>;  <span class="hljs-comment">//等号右侧的表达式`10`其类型为`整型字面值常量`，可以转换成`int整型常量`</span><br><span class="hljs-type">const</span> <span class="hljs-type">int</span> &amp;y = r*<span class="hljs-number">2</span>+<span class="hljs-number">3</span>;  <span class="hljs-comment">//等号右侧表达式的计算结果同样为`整型字面值常量`</span><br></code></pre></td></tr></table></figure><p>​</p></li><li><p><strong>顶层const</strong>:若对象<strong>【自身是一个常量】</strong>，不可变，则自身就是<code>顶层const</code></p><figure class="highlight c++"><table><tr><td class="gutter"><pre><span class="line">1</span><br></pre></td><td class="code"><pre><code class="hljs c++"><span class="hljs-type">const</span> <span class="hljs-type">int</span> x = <span class="hljs-number">1</span>;  <span class="hljs-comment">//x就是一个顶层const</span><br></code></pre></td></tr></table></figure><p>​</p></li></ul>]]></content>
    
    
    
  </entry>
  
  
  
  <entry>
    <title>About-Git</title>
    <link href="/2022/07/02/About-Git/"/>
    <url>/2022/07/02/About-Git/</url>
    
    <content type="html"><![CDATA[<h1 id="配置无密钥登录"><a href="#配置无密钥登录" class="headerlink" title="配置无密钥登录"></a>配置无密钥登录</h1><figure class="highlight bash"><table><tr><td class="gutter"><pre><span class="line">1</span><br><span class="line">2</span><br><span class="line">3</span><br><span class="line">4</span><br></pre></td><td class="code"><pre><code class="hljs bash"><span class="hljs-built_in">cd</span> ~/.ssh<br><span class="hljs-built_in">cat</span> id_rsa.pub  <br><br><br></code></pre></td></tr></table></figure><h4 id="复制公钥之后粘贴到这里"><a href="#复制公钥之后粘贴到这里" class="headerlink" title="复制公钥之后粘贴到这里"></a>复制公钥之后粘贴到这里</h4><ul><li><img src="/../img/1656770357265.png" alt="avatar"></li></ul><p>之后选中你要git clone 的仓库  </p><h3 id="在指定目录下"><a href="#在指定目录下" class="headerlink" title="在指定目录下"></a>在指定目录下</h3><figure class="highlight crmsh"><table><tr><td class="gutter"><pre><span class="line">1</span><br><span class="line">2</span><br><span class="line">3</span><br><span class="line">4</span><br><span class="line">5</span><br><span class="line">6</span><br><span class="line">7</span><br><span class="line">8</span><br><span class="line">9</span><br><span class="line">10</span><br><span class="line">11</span><br><span class="line">12</span><br><span class="line">13</span><br><span class="line">14</span><br><span class="line">15</span><br><span class="line">16</span><br><span class="line">17</span><br><span class="line">18</span><br><span class="line">19</span><br><span class="line">20</span><br><span class="line">21</span><br><span class="line">22</span><br><span class="line">23</span><br><span class="line">24</span><br><span class="line">25</span><br></pre></td><td class="code"><pre><code class="hljs crmsh">git <span class="hljs-keyword">clone</span>  <span class="hljs-title">&#x27;&#x27; 这里跟ssh</span> 地址 &#x27;&#x27;<br>git init 初始化 在当前目录新建一个Git代码库<br>git add  . (. 表示所有文件 或者可以指定需要单独提交文件)<br><span class="hljs-comment"># 通过add只是将文件或目录添加到了index暂存区，使用commit可以实现将暂存区的文件提交到本地仓库。</span><br>git commit -m <span class="hljs-string">&quot; 这里是提交说明&quot;</span><br>git push <br><span class="hljs-comment">#本地的master分支推送到origin主机，同时指定origin为默认主机，后面就可以不加任何参数使用git push了，-u 参数指定一个默认主机</span><br>git push -u origin <span class="hljs-keyword">master</span><br><span class="hljs-title">克隆版本库的时候，所使用的远程主机自动被Git</span>命名为origin。如果想用其他的主机名，需要用git clone命令的-o选项指定。<br><br><br><span class="hljs-comment">#查看指定文件状态</span><br>git status [filename]<br><br><span class="hljs-comment">#查看所有文件状态</span><br>git status<br><br><br><span class="hljs-comment"># 新建一个分支，但依然停留在当前分支，使用：</span><br>git branch [branch-name]<br><span class="hljs-comment"># 切换分支</span><br><span class="hljs-comment"># 如果name为-则为上一个分支</span><br><br><br><br></code></pre></td></tr></table></figure><p><img src="/../img/1656770632965.png" alt="1656770632965"></p><h3 id="下面是我参考的链接"><a href="#下面是我参考的链接" class="headerlink" title="下面是我参考的链接"></a>下面是我参考的链接</h3><figure class="highlight awk"><table><tr><td class="gutter"><pre><span class="line">1</span><br></pre></td><td class="code"><pre><code class="hljs awk">https:<span class="hljs-regexp">//</span>www.cnblogs.com<span class="hljs-regexp">/syp172654682/</span>p/<span class="hljs-number">7689328</span>.html<br></code></pre></td></tr></table></figure>]]></content>
    
    
    
    <tags>
      
      <tag>Git</tag>
      
    </tags>
    
  </entry>
  
  
  
  <entry>
    <title>About RPC</title>
    <link href="/2022/06/27/About-RPC/"/>
    <url>/2022/06/27/About-RPC/</url>
    
    <content type="html"><![CDATA[]]></content>
    
    
    
  </entry>
  
  
  
  <entry>
    <title>About Hexo</title>
    <link href="/2022/06/27/About-Hexo/"/>
    <url>/2022/06/27/About-Hexo/</url>
    
    <content type="html"><![CDATA[<h3 id="关于Hexo"><a href="#关于Hexo" class="headerlink" title="关于Hexo"></a>关于Hexo</h3><p><a href="https://link.zhihu.com/?target=https://hexo.io/zh-cn/">Hexo</a>是一个快速、简洁且高效的博客框架。Hexo 使用 <a href="https://link.zhihu.com/?target=http://daringfireball.net/projects/markdown/">Markdown</a>（或其他渲染引擎）解析文章，在几秒内，即可利用靓丽的主题生成静态网页。即把用户的markdown文件，按照指定的主题解析成静态网页。</p><h3 id="如何部署"><a href="#如何部署" class="headerlink" title="如何部署"></a>如何部署</h3><p>windows 需要安装Git</p><p>安装Node.js</p><figure class="highlight awk"><table><tr><td class="gutter"><pre><span class="line">1</span><br><span class="line">2</span><br></pre></td><td class="code"><pre><code class="hljs awk">https:<span class="hljs-regexp">//</span>nodejs.org<span class="hljs-regexp">/en/</span>download/ 访问官方网站下载<br>使用 Node.js 官方安装程序时，请确保勾选 Add to PATH 选项（默认已勾选）<br></code></pre></td></tr></table></figure><p>安装Hexo </p><figure class="highlight avrasm"><table><tr><td class="gutter"><pre><span class="line">1</span><br></pre></td><td class="code"><pre><code class="hljs avrasm">npm install -g hexo-<span class="hljs-keyword">cli</span><br></code></pre></td></tr></table></figure><p>验证是否安装成功</p><figure class="highlight ebnf"><table><tr><td class="gutter"><pre><span class="line">1</span><br></pre></td><td class="code"><pre><code class="hljs ebnf"><span class="hljs-attribute">hexo -v</span><br></code></pre></td></tr></table></figure><p>开始创建博客</p><figure class="highlight gherkin"><table><tr><td class="gutter"><pre><span class="line">1</span><br><span class="line">2</span><br><span class="line">3</span><br></pre></td><td class="code"><pre><code class="hljs gherkin">hexo  init <span class="hljs-variable">&lt;folder&gt;</span> <span class="hljs-comment"># 初始化该 文件架</span><br>cd <span class="hljs-variable">&lt;folder&gt;</span><br>npm install  <span class="hljs-comment"># 更新npm包的依赖</span><br></code></pre></td></tr></table></figure><p>预览页面  执行下列指令 即可预览页面 </p><figure class="highlight verilog"><table><tr><td class="gutter"><pre><span class="line">1</span><br><span class="line">2</span><br><span class="line">3</span><br><span class="line">4</span><br><span class="line">5</span><br><span class="line">6</span><br></pre></td><td class="code"><pre><code class="hljs verilog">hexo clean<br># 清除缓存，可用简略写法 hexo cl<br>hexo <span class="hljs-keyword">generate</span><br># 生成静态页面，可用简略写法 hexo g<br>hexo server<br># 本地运行，可用简略写法 hexo s<br></code></pre></td></tr></table></figure><h3 id="常用命令"><a href="#常用命令" class="headerlink" title="常用命令"></a>常用命令</h3>]]></content>
    
    
    
    <tags>
      
      <tag>hexo</tag>
      
    </tags>
    
  </entry>
  
  
  
  
</search>
